zlgcan-0.2.6.dist-info/METADATA
zlgcan-0.2.6.dist-info/WHEEL
zlgcan-0.2.6.dist-info/entry_points.txt
zlgcan-0.2.6.dist-info/licenses/LICENSE.txt
zlgcan/__init__.py
zlgcan/zlgcan.py
zlgcan_driver/__init__.py
zlgcan_driver/zlgcan_driver.cpython-39-x86_64-linux-gnu.so
zlgcan-0.2.6.dist-info/RECORD
