Metadata-Version: 2.4
Name: zlgcan
Version: 0.2.6
Classifier: Programming Language :: Rust
Classifier: Programming Language :: Python :: Implementation :: CPython
Classifier: Programming Language :: Python :: Implementation :: PyPy
Requires-Dist: python-can>=4.0.0
License-File: LICENSE.txt
Summary: Python wrapper for zlgcan driver.
Author: Jesse Smith
License: LGPL v3
Requires-Python: >=3.8
Project-URL: homepage, https://github.com/jesses2025smith/zlgcan-driver
Project-URL: repository, https://github.com/jesses2025smith/zlgcan-driver
